MANIFEST.in
README.md
setup.cfg
setup.py
datapipe/__init__.py
datapipe/exceptions.py
datapipe/gv.py
datapipe/models.py
datapipe/pipe.py
datapipe/pipeline.py
datapipe/tasks.py
datapipe.egg-info/PKG-INFO
datapipe.egg-info/SOURCES.txt
datapipe.egg-info/dependency_links.txt
datapipe.egg-info/requires.txt
datapipe.egg-info/top_level.txt
datapipe/migrations/0001_initial.py
datapipe/migrations/__init__.py
datapipe/utils/__init__.py
datapipe/utils/datastructures.py
datapipe/utils/iter.py