Metadata-Version: 1.1
Name: datapipe
Version: 0.1.0
Summary: Data Processing Framework that allow you to processing data like building blocks
Home-page: https://github.com/yjmade/datapipe
Author: Jay Young(yjmade)
Author-email: dev@yjmade.net
License: MIT
Keywords: data processing pipeline
Platform: UNKNOWN
Classifier: Intended Audience :: Developers
